rulebook_pylint/__init__.py
rulebook_pylint/files.py
rulebook_pylint/messages.py
rulebook_pylint/nodes.py
rulebook_pylint/checkers/__init__.py
rulebook_pylint/checkers/abstract_class_definition.py
rulebook_pylint/checkers/block_comment_trim.py
rulebook_pylint/checkers/built_in_function_position.py
rulebook_pylint/checkers/case_separator.py
rulebook_pylint/checkers/class_name_abbreviation.py
rulebook_pylint/checkers/comment_space.py
rulebook_pylint/checkers/comment_trim.py
rulebook_pylint/checkers/duplicate_blank_line.py
rulebook_pylint/checkers/duplicate_blank_line_in_block_comment.py
rulebook_pylint/checkers/duplicate_blank_line_in_comment.py
rulebook_pylint/checkers/duplicate_space.py
rulebook_pylint/checkers/empty_parentheses_clip.py
rulebook_pylint/checkers/exception_inheritance.py
rulebook_pylint/checkers/file_size.py
rulebook_pylint/checkers/illegal_class_name_suffix.py
rulebook_pylint/checkers/inner_class_position.py
rulebook_pylint/checkers/member_order.py
rulebook_pylint/checkers/member_separator.py
rulebook_pylint/checkers/nested_if_else.py
rulebook_pylint/checkers/parameter_wrap.py
rulebook_pylint/checkers/parentheses_trim.py
rulebook_pylint/checkers/redundant_default.py
rulebook_pylint/checkers/required_generics_name.py
rulebook_pylint/checkers/rulebook_checkers.py
rulebook_pylint/checkers/short_block_comment_clip.py
rulebook_pylint/checkers/string_quotes.py
rulebook_pylint/checkers/todo_comment.py
rulebook_pylint/checkers/trailing_comma.py
rulebook_pylint/checkers/unnecessary_blank_line_after_colon.py
rulebook_pylint/checkers/unnecessary_blank_line_before_package.py
rulebook_pylint/checkers/unnecessary_switch.py
rulebook_pylint/resources/google_pylintrc
rulebook_pylint/resources/messages.json
rulebook_pylint/resources/standard_pylintrc
rulebook_pylint-0.2.dist-info/licenses/LICENSE
rulebook_pylint-0.2.dist-info/METADATA
rulebook_pylint-0.2.dist-info/WHEEL
rulebook_pylint-0.2.dist-info/top_level.txt
rulebook_pylint-0.2.dist-info/RECORD
