Metadata-Version: 2.4
Name: rulebook-pylint
Version: 0.2
Summary: Extended lint rules for JVM and Python
Author-email: Hendra Anggrian <hanggrian@proton.me>
License: Apache-2.0
Project-URL: Source Code, https://github.com/hanggrian/rulebook
Project-URL: Bug Tracker, https://github.com/hanggrian/rulebook/issues
Keywords: lint rules,lint checkers
Classifier: Programming Language :: Python :: 3
Classifier: License :: OSI Approved :: Apache Software License
Classifier: Operating System :: OS Independent
Requires-Python: >=3.8
License-File: LICENSE
Dynamic: license-file
